scikit_surgeryvtk-2.3.1.dist-info/licenses/LICENSE
sksurgeryvtk/__init__.py
sksurgeryvtk/_version.py
sksurgeryvtk/camera/__init__.py
sksurgeryvtk/camera/vtk_camera_model.py
sksurgeryvtk/models/__init__.py
sksurgeryvtk/models/outline_render.py
sksurgeryvtk/models/surface_model_loader.py
sksurgeryvtk/models/voxelise.py
sksurgeryvtk/models/vtk_base_actor.py
sksurgeryvtk/models/vtk_base_model.py
sksurgeryvtk/models/vtk_cylinder_model.py
sksurgeryvtk/models/vtk_grid_model.py
sksurgeryvtk/models/vtk_image_model.py
sksurgeryvtk/models/vtk_point_model.py
sksurgeryvtk/models/vtk_sphere_model.py
sksurgeryvtk/models/vtk_surface_model.py
sksurgeryvtk/models/vtk_surface_model_directory_loader.py
sksurgeryvtk/models/vtk_tube_model.py
sksurgeryvtk/text/__init__.py
sksurgeryvtk/text/text_overlay.py
sksurgeryvtk/utils/__init__.py
sksurgeryvtk/utils/matrix_utils.py
sksurgeryvtk/utils/platform_utils.py
sksurgeryvtk/utils/polydata_utils.py
sksurgeryvtk/utils/projection_utils.py
sksurgeryvtk/widgets/__init__.py
sksurgeryvtk/widgets/vtk_base_calibrated_window.py
sksurgeryvtk/widgets/vtk_interlaced_stereo_window.py
sksurgeryvtk/widgets/vtk_lus_simulator.py
sksurgeryvtk/widgets/vtk_overlay_window.py
sksurgeryvtk/widgets/vtk_rendering_generator.py
sksurgeryvtk/widgets/vtk_reslice_widget.py
sksurgeryvtk/widgets/vtk_zbuffer_window.py
tests/camera/__init__.py
tests/camera/test_liver_overlay.py
tests/camera/test_vtk_camera_model.py
tests/models/__init__.py
tests/models/test_surface_model_loader.py
tests/models/test_voxelise.py
tests/models/test_vtk_cylinder_model.py
tests/models/test_vtk_image_model.py
tests/models/test_vtk_point_model.py
tests/models/test_vtk_sphere_model.py
tests/models/test_vtk_surface_model.py
tests/models/test_vtk_surface_model_directory_loader.py
tests/models/test_vtk_tube_model.py
tests/models/test_vtk_unstructured_grid.py
tests/utils/__init__.py
tests/utils/test_matrix_utills.py
tests/utils/test_polydata_utils.py
tests/utils/test_projection_utils.py
tests/widgets/__init__.py
scikit_surgeryvtk-2.3.1.dist-info/METADATA
scikit_surgeryvtk-2.3.1.dist-info/WHEEL
scikit_surgeryvtk-2.3.1.dist-info/top_level.txt
scikit_surgeryvtk-2.3.1.dist-info/RECORD
