Metadata-Version: 2.4
Name: scikit-surgeryvtk
Version: 2.3.1
Summary: scikit-surgeryvtk uses VTK for Image Guided Surgery applications
Home-page: https://github.com/SciKit-Surgery/scikit-surgeryvtk
Author: Thomas Dowrick
Author-email: t.dowrick@ucl.ac.uk
License: BSD-3 license
Keywords: medical imaging
Classifier: Development Status :: 5 - Production/Stable
Classifier: Intended Audience :: Developers
Classifier: Intended Audience :: Healthcare Industry
Classifier: Intended Audience :: Information Technology
Classifier: Intended Audience :: Science/Research
Classifier: License :: OSI Approved :: BSD License
Classifier: Programming Language :: Python
Classifier: Programming Language :: Python :: 3.8
Classifier: Topic :: Scientific/Engineering :: Information Analysis
Classifier: Topic :: Scientific/Engineering :: Medical Science Apps.
License-File: LICENSE
Requires-Dist: numpy>=1.11
Requires-Dist: vtk>=9.5.0
Requires-Dist: PySide6<6.10.0,>=6.5.1.1
Requires-Dist: opencv-contrib-python-headless>=4.2.0.32
Requires-Dist: scikit-surgerycore>=0.1.7
Requires-Dist: scikit-surgeryimage>=0.10.1
Dynamic: author
Dynamic: author-email
Dynamic: classifier
Dynamic: description
Dynamic: description-content-type
Dynamic: home-page
Dynamic: keywords
Dynamic: license
Dynamic: license-file
Dynamic: requires-dist
Dynamic: summary
